tsuraika/__init__.py
tsuraika/cli.py
tsuraika/client.py
tsuraika/common.py
tsuraika/server.py
tsuraika-1.0.0.dist-info/LICENSE
tsuraika-1.0.0.dist-info/METADATA
tsuraika-1.0.0.dist-info/WHEEL
tsuraika-1.0.0.dist-info/entry_points.txt
tsuraika-1.0.0.dist-info/top_level.txt
tsuraika-1.0.0.dist-info/RECORD
